{"resume": "LVMH achieved revenue of \u20ac84.7 billion in 2024 with 1% organic growth despite a challenging global economic environment and high post-Covid comparisons. The company maintained strong profitability with a 23.1% operating margin and significantly increased free cash flow by 29% to \u20ac10.5 billion. The fourth quarter showed acceleration driven by Asia, the United States and Europe, while the company continued investments in sustainability and maintained its position as France's largest private-sector employer.", "ton": "neutre", "raison_ton": "The company shows resilience with positive organic growth and strong cash flow generation, but faces revenue decline in absolute terms and significant profit pressures from currency headwinds.", "kpis": [{"nom": "Revenue", "valeur": "\u20ac84.7 billion", "variation": "-2%", "sens": "neg"}, {"nom": "Organic Revenue Growth", "valeur": "1%", "variation": "+1%", "sens": "pos"}, {"nom": "Profit from Recurring Operations", "valeur": "\u20ac19.6 billion", "variation": "-14%", "sens": "neg"}, {"nom": "Operating Margin", "valeur": "23.1%", "variation": "N/A", "sens": "pos"}, {"nom": "Free Cash Flow", "valeur": "\u20ac10.5 billion", "variation": "+29%", "sens": "pos"}, {"nom": "Net Financial Debt", "valeur": "\u20ac9.2 billion", "variation": "-14%", "sens": "pos"}], "themes": ["Resilience in challenging global environment", "Geographic diversification with acceleration in Asia, US and Europe", "Sustainability leadership with LIFE 360 environmental program achievements", "Innovation and brand desirability across all business segments", "Strategic investments in production facilities and retail network expansion", "Major social impact as France's largest private-sector employer"], "risques": ["Substantial negative impact from exchange rate fluctuations affecting profitability", "Ongoing normalization of demand in Wines & Spirits particularly in China", "Uncertain geopolitical and macroeconomic environment affecting consumer spending"], "opportunites": ["Double-digit revenue growth in Japan and continued Asian market expansion", "Sephora's remarkable performance with double-digit growth and market share gains", "Acceleration in Q4 momentum providing positive outlook for 2025"]}